Workbook
Name r_base_m: Inputs!$B$17
Name r_high_m: Inputs!$B$18
Name r_low_m: Inputs!$B$16

Sheet Inputs
A1: LoanID | B1: Principal | C1: AnnualRate | D1: TermMonths | E1: StartMonth | F1: PD_Annual | G1: LGD | H1: Note
A2: L1 | B2: 25000 | C2: 0.08 | D2: 60 | E2: 1 | F2: 0.04 | G2: 0.4 | H2: base example
A3: L2 | B3: 15000 | C3: 0.065 | D3: 60 | E3: 1 | F3: 0.03 | G3: 0.5
A4: L3 | B4: 30000 | C4: 0.072 | D4: 60 | E4: 1 | F4: 0.05 | G4: 0.25
A5: L4 | B5: 12000 | C5: 0.055 | D5: 60 | E5: 1 | F5: 0.02 | G5: 0.6
A6: L5 | B6: 40000 | C6: 0.09 | D6: 60 | E6: 1 | F6: 0.06 | G6: 0.5
A7: L6 | B7: 18000 | C7: 0.068 | D7: 60 | E7: 1 | F7: 0.03 | G7: 0.45
A8: L7 | B8: 22000 | C8: 0.075 | D8: 60 | E8: 1 | F8: 0.04 | G8: 0.3
A9: L8 | B9: 50000 | C9: 0.085 | D9: 60 | E9: 1 | F9: 0.07 | G9: 0.2
A10: L9 | B10: 27000 | C10: 0.07 | D10: 60 | E10: 1 | F10: 0.04 | G10: 0.35
A11: L10 | B11: 10000 | C11: 0.06 | D11: 60 | E11: 1 | F11: 0.02 | G11: 0.4
A13: DiscRate_Low | B13: 0.03
A14: DiscRate_Base | B14: 0.05
A15: DiscRate_High | B15: 0.08
A16: DiscRate_Low_m | B16: =(1+B13)^(1/12)-1 -> 0.0024662698
A17: DiscRate_Base_m | B17: =(1+B14)^(1/12)-1 -> 0.0040741238
A18: DiscRate_High_m | B18: =(1+B15)^(1/12)-1 -> 0.0064340301

Sheet Schedule
A1: LoanID | B1: Month | C1: Beginning Balance | D1: Payment | E1: Interest | F1: Principal | G1: Ending Balance | H1: Cash Flow
A2: =Inputs!$A$2 -> L1 | B2: 1 | C2: =Inputs!$B$2 -> 25000 | D2: =-PMT(Inputs!$C$2/12, Inputs!$D$2, Inputs!$B$2) -> 506.90986 | E2: =C2 * (Inputs!$C$2/12) -> 166.66667 | F2: =D2 - E2 -> 340.24319 | G2: =C2 - F2 -> 24659.757 | H2: =D2 -> 506.90986
A3: =Inputs!$A$2 -> L1 | B3: 2 | C3: =G2 -> 24659.757 | D3: =-PMT(Inputs!$C$2/12, Inputs!$D$2, Inputs!$B$2) -> 506.90986 | E3: =C3 * (Inputs!$C$2/12) -> 164.39838 | F3: =D3 - E3 -> 342.51148 | G3: =C3 - F3 -> 24317.245 | H3: =D3 -> 506.90986
A4: =Inputs!$A$2 -> L1 | B4: 3 | C4: =G3 -> 24317.245 | D4: =-PMT(Inputs!$C$2/12, Inputs!$D$2, Inputs!$B$2) -> 506.90986 | E4: =C4 * (Inputs!$C$2/12) -> 162.11497 | F4: =D4 - E4 -> 344.79489 | G4: =C4 - F4 -> 23972.45 | H4: =D4 -> 506.90986
A5: =Inputs!$A$2 -> L1 | B5: 4 | C5: =G4 -> 23972.45 | D5: =-PMT(Inputs!$C$2/12, Inputs!$D$2, Inputs!$B$2) -> 506.90986 | E5: =C5 * (Inputs!$C$2/12) -> 159.81634 | F5: =D5 - E5 -> 347.09352 | G5: =C5 - F5 -> 23625.357 | H5: =D5 -> 506.90986
A6: =Inputs!$A$2 -> L1 | B6: 5 | C6: =G5 -> 23625.357 | D6: =-PMT(Inputs!$C$2/12, Inputs!$D$2, Inputs!$B$2) -> 506.90986 | E6: =C6 * (Inputs!$C$2/12) -> 157.50238 | F6: =D6 - E6 -> 349.40748 | G6: =C6 - F6 -> 23275.949 | H6: =D6 -> 506.90986
A7: =Inputs!$A$2 -> L1 | B7: 6 | C7: =G6 -> 23275.949 | D7: =-PMT(Inputs!$C$2/12, Inputs!$D$2, Inputs!$B$2) -> 506.90986 | E7: =C7 * (Inputs!$C$2/12) -> 155.173 | F7: =D7 - E7 -> 351.73686 | G7: =C7 - F7 -> 22924.213 | H7: =D7 -> 506.90986
A8: =Inputs!$A$2 -> L1 | B8: 7 | C8: =G7 -> 22924.213 | D8: =-PMT(Inputs!$C$2/12, Inputs!$D$2, Inputs!$B$2) -> 506.90986 | E8: =C8 * (Inputs!$C$2/12) -> 152.82808 | F8: =D8 - E8 -> 354.08177 | G8: =C8 - F8 -> 22570.131 | H8: =D8 -> 506.90986
A9: =Inputs!$A$2 -> L1 | B9: 8 | C9: =G8 -> 22570.131 | D9: =-PMT(Inputs!$C$2/12, Inputs!$D$2, Inputs!$B$2) -> 506.90986 | E9: =C9 * (Inputs!$C$2/12) -> 150.46754 | F9: =D9 - E9 -> 356.44232 | G9: =C9 - F9 -> 22213.688 | H9: =D9 -> 506.90986
A10: =Inputs!$A$2 -> L1 | B10: 9 | C10: =G9 -> 22213.688 | D10: =-PMT(Inputs!$C$2/12, Inputs!$D$2, Inputs!$B$2) -> 506.90986 | E10: =C10 * (Inputs!$C$2/12) -> 148.09126 | F10: =D10 - E10 -> 358.8186 | G10: =C10 - F10 -> 21854.87 | H10: =D10 -> 506.90986
A11: =Inputs!$A$2 -> L1 | B11: 10 | C11: =G10 -> 21854.87 | D11: =-PMT(Inputs!$C$2/12, Inputs!$D$2, Inputs!$B$2) -> 506.90986 | E11: =C11 * (Inputs!$C$2/12) -> 145.69913 | F11: =D11 - E11 -> 361.21072 | G11: =C11 - F11 -> 21493.659 | H11: =D11 -> 506.90986
A12: =Inputs!$A$2 -> L1 | B12: 11 | C12: =G11 -> 21493.659 | D12: =-PMT(Inputs!$C$2/12, Inputs!$D$2, Inputs!$B$2) -> 506.90986 | E12: =C12 * (Inputs!$C$2/12) -> 143.29106 | F12: =D12 - E12 -> 363.6188 | G12: =C12 - F12 -> 21130.04 | H12: =D12 -> 506.90986
A13: =Inputs!$A$2 -> L1 | B13: 12 | C13: =G12 -> 21130.04 | D13: =-PMT(Inputs!$C$2/12, Inputs!$D$2, Inputs!$B$2) -> 506.90986 | E13: =C13 * (Inputs!$C$2/12) -> 140.86694 | F13: =D13 - E13 -> 366.04292 | G13: =C13 - F13 -> 20763.997 | H13: =D13 -> 506.90986
A14: =Inputs!$A$2 -> L1 | B14: 13 | C14: =G13 -> 20763.997 | D14: =-PMT(Inputs!$C$2/12, Inputs!$D$2, Inputs!$B$2) -> 506.90986 | E14: =C14 * (Inputs!$C$2/12) -> 138.42665 | F14: =D14 - E14 -> 368.48321 | G14: =C14 - F14 -> 20395.514 | H14: =D14 -> 506.90986
... A61: =Inputs!$A$2 -> L1 | B61: 60 | C61: =G60 -> 503.55284 | D61: =-PMT(Inputs!$C$2/12, Inputs!$D$2, Inputs!$B$2) -> 506.90986 | E61: =C61 * (Inputs!$C$2/12) -> 3.3570189 | F61: =D61 - E61 -> 503.55284 | G61: =C61 - F61 -> -7.0485839e-12 | H61: =D61 -> 506.90986
A63: =Inputs!$A$3 -> L2 | B63: 1 | C63: =Inputs!$B$3 -> 15000 | D63: =-PMT(Inputs!$C$3/12, Inputs!$D$3, Inputs!$B$3) -> 293.49222 | E63: =C63 * (Inputs!$C$3/12) -> 81.25 | F63: =D63 - E63 -> 212.24222 | G63: =C63 - F63 -> 14787.758 | H63: =D63 -> 293.49222
A64: =Inputs!$A$3 -> L2 | B64: 2 | C64: =G63 -> 14787.758 | D64: =-PMT(Inputs!$C$3/12, Inputs!$D$3, Inputs!$B$3) -> 293.49222 | E64: =C64 * (Inputs!$C$3/12) -> 80.100355 | F64: =D64 - E64 -> 213.39187 | G64: =C64 - F64 -> 14574.366 | H64: =D64 -> 293.49222
A65: =Inputs!$A$3 -> L2 | B65: 3 | C65: =G64 -> 14574.366 | D65: =-PMT(Inputs!$C$3/12, Inputs!$D$3, Inputs!$B$3) -> 293.49222 | E65: =C65 * (Inputs!$C$3/12) -> 78.944482 | F65: =D65 - E65 -> 214.54774 | G65: =C65 - F65 -> 14359.818 | H65: =D65 -> 293.49222
A66: =Inputs!$A$3 -> L2 | B66: 4 | C66: =G65 -> 14359.818 | D66: =-PMT(Inputs!$C$3/12, Inputs!$D$3, Inputs!$B$3) -> 293.49222 | E66: =C66 * (Inputs!$C$3/12) -> 77.782348 | F66: =D66 - E66 -> 215.70987 | G66: =C66 - F66 -> 14144.108 | H66: =D66 -> 293.49222
A67: =Inputs!$A$3 -> L2 | B67: 5 | C67: =G66 -> 14144.108 | D67: =-PMT(Inputs!$C$3/12, Inputs!$D$3, Inputs!$B$3) -> 293.49222 | E67: =C67 * (Inputs!$C$3/12) -> 76.61392 | F67: =D67 - E67 -> 216.8783 | G67: =C67 - F67 -> 13927.23 | H67: =D67 -> 293.49222
A68: =Inputs!$A$3 -> L2 | B68: 6 | C68: =G67 -> 13927.23 | D68: =-PMT(Inputs!$C$3/12, Inputs!$D$3, Inputs!$B$3) -> 293.49222 | E68: =C68 * (Inputs!$C$3/12) -> 75.439162 | F68: =D68 - E68 -> 218.05306 | G68: =C68 - F68 -> 13709.177 | H68: =D68 -> 293.49222
A69: =Inputs!$A$3 -> L2 | B69: 7 | C69: =G68 -> 13709.177 | D69: =-PMT(Inputs!$C$3/12, Inputs!$D$3, Inputs!$B$3) -> 293.49222 | E69: =C69 * (Inputs!$C$3/12) -> 74.258042 | F69: =D69 - E69 -> 219.23418 | G69: =C69 - F69 -> 13489.943 | H69: =D69 -> 293.49222
A70: =Inputs!$A$3 -> L2 | B70: 8 | C70: =G69 -> 13489.943 | D70: =-PMT(Inputs!$C$3/12, Inputs!$D$3, Inputs!$B$3) -> 293.49222 | E70: =C70 * (Inputs!$C$3/12) -> 73.070523 | F70: =D70 - E70 -> 220.4217 | G70: =C70 - F70 -> 13269.521 | H70: =D70 -> 293.49222
A71: =Inputs!$A$3 -> L2 | B71: 9 | C71: =G70 -> 13269.521 | D71: =-PMT(Inputs!$C$3/12, Inputs!$D$3, Inputs!$B$3) -> 293.49222 | E71: =C71 * (Inputs!$C$3/12) -> 71.876572 | F71: =D71 - E71 -> 221.61565 | G71: =C71 - F71 -> 13047.905 | H71: =D71 -> 293.49222
A72: =Inputs!$A$3 -> L2 | B72: 10 | C72: =G71 -> 13047.905 | D72: =-PMT(Inputs!$C$3/12, Inputs!$D$3, Inputs!$B$3) -> 293.49222 | E72: =C72 * (Inputs!$C$3/12) -> 70.676154 | F72: =D72 - E72 -> 222.81607 | G72: =C72 - F72 -> 12825.089 | H72: =D72 -> 293.49222
A73: =Inputs!$A$3 -> L2 | B73: 11 | C73: =G72 -> 12825.089 | D73: =-PMT(Inputs!$C$3/12, Inputs!$D$3, Inputs!$B$3) -> 293.49222 | E73: =C73 * (Inputs!$C$3/12) -> 69.469234 | F73: =D73 - E73 -> 224.02299 | G73: =C73 - F73 -> 12601.066 | H73: =D73 -> 293.49222
A74: =Inputs!$A$3 -> L2 | B74: 12 | C74: =G73 -> 12601.066 | D74: =-PMT(Inputs!$C$3/12, Inputs!$D$3, Inputs!$B$3) -> 293.49222 | E74: =C74 * (Inputs!$C$3/12) -> 68.255776 | F74: =D74 - E74 -> 225.23645 | G74: =C74 - F74 -> 12375.83 | H74: =D74 -> 293.49222
A75: =Inputs!$A$3 -> L2 | B75: 13 | C75: =G74 -> 12375.83 | D75: =-PMT(Inputs!$C$3/12, Inputs!$D$3, Inputs!$B$3) -> 293.49222 | E75: =C75 * (Inputs!$C$3/12) -> 67.035745 | F75: =D75 - E75 -> 226.45648 | G75: =C75 - F75 -> 12149.373 | H75: =D75 -> 293.49222
... A122: =Inputs!$A$3 -> L2 | B122: 60 | C122: =G121 -> 291.91104 | D122: =-PMT(Inputs!$C$3/12, Inputs!$D$3, Inputs!$B$3) -> 293.49222 | E122: =C122 * (Inputs!$C$3/12) -> 1.5811848 | F122: =D122 - E122 -> 291.91104 | G122: =C122 - F122 -> 0 | H122: =D122 -> 293.49222
A124: =Inputs!$A$4 -> L3 | B124: 1 | C124: =Inputs!$B$4 -> 30000 | D124: =-PMT(Inputs!$C$4/12, Inputs!$D$4, Inputs!$B$4) -> 596.87084 | E124: =C124 * (Inputs!$C$4/12) -> 180 | F124: =D124 - E124 -> 416.87084 | G124: =C124 - F124 -> 29583.129 | H124: =D124 -> 596.87084
A125: =Inputs!$A$4 -> L3 | B125: 2 | C125: =G124 -> 29583.129 | D125: =-PMT(Inputs!$C$4/12, Inputs!$D$4, Inputs!$B$4) -> 596.87084 | E125: =C125 * (Inputs!$C$4/12) -> 177.49877 | F125: =D125 - E125 -> 419.37207 | G125: =C125 - F125 -> 29163.757 | H125: =D125 -> 596.87084
A126: =Inputs!$A$4 -> L3 | B126: 3 | C126: =G125 -> 29163.757 | D126: =-PMT(Inputs!$C$4/12, Inputs!$D$4, Inputs!$B$4) -> 596.87084 | E126: =C126 * (Inputs!$C$4/12) -> 174.98254 | F126: =D126 - E126 -> 421.8883 | G126: =C126 - F126 -> 28741.869 | H126: =D126 -> 596.87084
A127: =Inputs!$A$4 -> L3 | B127: 4 | C127: =G126 -> 28741.869 | D127: =-PMT(Inputs!$C$4/12, Inputs!$D$4, Inputs!$B$4) -> 596.87084 | E127: =C127 * (Inputs!$C$4/12) -> 172.45121 | F127: =D127 - E127 -> 424.41963 | G127: =C127 - F127 -> 28317.449 | H127: =D127 -> 596.87084
A128: =Inputs!$A$4 -> L3 | B128: 5 | C128: =G127 -> 28317.449 | D128: =-PMT(Inputs!$C$4/12, Inputs!$D$4, Inputs!$B$4) -> 596.87084 | E128: =C128 * (Inputs!$C$4/12) -> 169.90469 | F128: =D128 - E128 -> 426.96615 | G128: =C128 - F128 -> 27890.483 | H128: =D128 -> 596.87084
A129: =Inputs!$A$4 -> L3 | B129: 6 | C129: =G128 -> 27890.483 | D129: =-PMT(Inputs!$C$4/12, Inputs!$D$4, Inputs!$B$4) -> 596.87084 | E129: =C129 * (Inputs!$C$4/12) -> 167.3429 | F129: =D129 - E129 -> 429.52795 | G129: =C129 - F129 -> 27460.955 | H129: =D129 -> 596.87084
A130: =Inputs!$A$4 -> L3 | B130: 7 | C130: =G129 -> 27460.955 | D130: =-PMT(Inputs!$C$4/12, Inputs!$D$4, Inputs!$B$4) -> 596.87084 | E130: =C130 * (Inputs!$C$4/12) -> 164.76573 | F130: =D130 - E130 -> 432.10511 | G130: =C130 - F130 -> 27028.85 | H130: =D130 -> 596.87084
A131: =Inputs!$A$4 -> L3 | B131: 8 | C131: =G130 -> 27028.85 | D131: =-PMT(Inputs!$C$4/12, Inputs!$D$4, Inputs!$B$4) -> 596.87084 | E131: =C131 * (Inputs!$C$4/12) -> 162.1731 | F131: =D131 - E131 -> 434.69774 | G131: =C131 - F131 -> 26594.152 | H131: =D131 -> 596.87084
A132: =Inputs!$A$4 -> L3 | B132: 9 | C132: =G131 -> 26594.152 | D132: =-PMT(Inputs!$C$4/12, Inputs!$D$4, Inputs!$B$4) -> 596.87084 | E132: =C132 * (Inputs!$C$4/12) -> 159.56491 | F132: =D132 - E132 -> 437.30593 | G132: =C132 - F132 -> 26156.846 | H132: =D132 -> 596.87084
A133: =Inputs!$A$4 -> L3 | B133: 10 | C133: =G132 -> 26156.846 | D133: =-PMT(Inputs!$C$4/12, Inputs!$D$4, Inputs!$B$4) -> 596.87084 | E133: =C133 * (Inputs!$C$4/12) -> 156.94108 | F133: =D133 - E133 -> 439.92977 | G133: =C133 - F133 -> 25716.916 | H133: =D133 -> 596.87084
A134: =Inputs!$A$4 -> L3 | B134: 11 | C134: =G133 -> 25716.916 | D134: =-PMT(Inputs!$C$4/12, Inputs!$D$4, Inputs!$B$4) -> 596.87084 | E134: =C134 * (Inputs!$C$4/12) -> 154.3015 | F134: =D134 - E134 -> 442.56935 | G134: =C134 - F134 -> 25274.347 | H134: =D134 -> 596.87084
A135: =Inputs!$A$4 -> L3 | B135: 12 | C135: =G134 -> 25274.347 | D135: =-PMT(Inputs!$C$4/12, Inputs!$D$4, Inputs!$B$4) -> 596.87084 | E135: =C135 * (Inputs!$C$4/12) -> 151.64608 | F135: =D135 - E135 -> 445.22476 | G135: =C135 - F135 -> 24829.122 | H135: =D135 -> 596.87084
A136: =Inputs!$A$4 -> L3 | B136: 13 | C136: =G135 -> 24829.122 | D136: =-PMT(Inputs!$C$4/12, Inputs!$D$4, Inputs!$B$4) -> 596.87084 | E136: =C136 * (Inputs!$C$4/12) -> 148.97473 | F136: =D136 - E136 -> 447.89611 | G136: =C136 - F136 -> 24381.226 | H136: =D136 -> 596.87084
... A183: =Inputs!$A$4 -> L3 | B183: 60 | C183: =G182 -> 593.31098 | D183: =-PMT(Inputs!$C$4/12, Inputs!$D$4, Inputs!$B$4) -> 596.87084 | E183: =C183 * (Inputs!$C$4/12) -> 3.5598659 | F183: =D183 - E183 -> 593.31098 | G183: =C183 - F183 -> 9.4360075e-12 | H183: =D183 -> 596.87084
A185: =Inputs!$A$5 -> L4 | B185: 1 | C185: =Inputs!$B$5 -> 12000 | D185: =-PMT(Inputs!$C$5/12, Inputs!$D$5, Inputs!$B$5) -> 229.21395 | E185: =C185 * (Inputs!$C$5/12) -> 55 | F185: =D185 - E185 -> 174.21395 | G185: =C185 - F185 -> 11825.786 | H185: =D185 -> 229.21395
A186: =Inputs!$A$5 -> L4 | B186: 2 | C186: =G185 -> 11825.786 | D186: =-PMT(Inputs!$C$5/12, Inputs!$D$5, Inputs!$B$5) -> 229.21395 | E186: =C186 * (Inputs!$C$5/12) -> 54.201519 | F186: =D186 - E186 -> 175.01243 | G186: =C186 - F186 -> 11650.774 | H186: =D186 -> 229.21395
A187: =Inputs!$A$5 -> L4 | B187: 3 | C187: =G186 -> 11650.774 | D187: =-PMT(Inputs!$C$5/12, Inputs!$D$5, Inputs!$B$5) -> 229.21395 | E187: =C187 * (Inputs!$C$5/12) -> 53.399379 | F187: =D187 - E187 -> 175.81457 | G187: =C187 - F187 -> 11474.959 | H187: =D187 -> 229.21395
A188: =Inputs!$A$5 -> L4 | B188: 4 | C188: =G187 -> 11474.959 | D188: =-PMT(Inputs!$C$5/12, Inputs!$D$5, Inputs!$B$5) -> 229.21395 | E188: =C188 * (Inputs!$C$5/12) -> 52.593562 | F188: =D188 - E188 -> 176.62038 | G188: =C188 - F188 -> 11298.339 | H188: =D188 -> 229.21395
A189: =Inputs!$A$5 -> L4 | B189: 5 | C189: =G188 -> 11298.339 | D189: =-PMT(Inputs!$C$5/12, Inputs!$D$5, Inputs!$B$5) -> 229.21395 | E189: =C189 * (Inputs!$C$5/12) -> 51.784052 | F189: =D189 - E189 -> 177.42989 | G189: =C189 - F189 -> 11120.909 | H189: =D189 -> 229.21395
A190: =Inputs!$A$5 -> L4 | B190: 6 | C190: =G189 -> 11120.909 | D190: =-PMT(Inputs!$C$5/12, Inputs!$D$5, Inputs!$B$5) -> 229.21395 | E190: =C190 * (Inputs!$C$5/12) -> 50.970832 | F190: =D190 - E190 -> 178.24311 | G190: =C190 - F190 -> 10942.666 | H190: =D190 -> 229.21395
A191: =Inputs!$A$5 -> L4 | B191: 7 | C191: =G190 -> 10942.666 | D191: =-PMT(Inputs!$C$5/12, Inputs!$D$5, Inputs!$B$5) -> 229.21395 | E191: =C191 * (Inputs!$C$5/12) -> 50.153884 | F191: =D191 - E191 -> 179.06006 | G191: =C191 - F191 -> 10763.606 | H191: =D191 -> 229.21395
A192: =Inputs!$A$5 -> L4 | B192: 8 | C192: =G191 -> 10763.606 | D192: =-PMT(Inputs!$C$5/12, Inputs!$D$5, Inputs!$B$5) -> 229.21395 | E192: =C192 * (Inputs!$C$5/12) -> 49.333192 | F192: =D192 - E192 -> 179.88075 | G192: =C192 - F192 -> 10583.725 | H192: =D192 -> 229.21395
A193: =Inputs!$A$5 -> L4 | B193: 9 | C193: =G192 -> 10583.725 | D193: =-PMT(Inputs!$C$5/12, Inputs!$D$5, Inputs!$B$5) -> 229.21395 | E193: =C193 * (Inputs!$C$5/12) -> 48.508739 | F193: =D193 - E193 -> 180.70521 | G193: =C193 - F193 -> 10403.02 | H193: =D193 -> 229.21395
A194: =Inputs!$A$5 -> L4 | B194: 10 | C194: =G193 -> 10403.02 | D194: =-PMT(Inputs!$C$5/12, Inputs!$D$5, Inputs!$B$5) -> 229.21395 | E194: =C194 * (Inputs!$C$5/12) -> 47.680507 | F194: =D194 - E194 -> 181.53344 | G194: =C194 - F194 -> 10221.486 | H194: =D194 -> 229.21395
A195: =Inputs!$A$5 -> L4 | B195: 11 | C195: =G194 -> 10221.486 | D195: =-PMT(Inputs!$C$5/12, Inputs!$D$5, Inputs!$B$5) -> 229.21395 | E195: =C195 * (Inputs!$C$5/12) -> 46.848478 | F195: =D195 - E195 -> 182.36547 | G195: =C195 - F195 -> 10039.121 | H195: =D195 -> 229.21395
A196: =Inputs!$A$5 -> L4 | B196: 12 | C196: =G195 -> 10039.121 | D196: =-PMT(Inputs!$C$5/12, Inputs!$D$5, Inputs!$B$5) -> 229.21395 | E196: =C196 * (Inputs!$C$5/12) -> 46.012637 | F196: =D196 - E196 -> 183.20131 | G196: =C196 - F196 -> 9855.9194 | H196: =D196 -> 229.21395
A197: =Inputs!$A$5 -> L4 | B197: 13 | C197: =G196 -> 9855.9194 | D197: =-PMT(Inputs!$C$5/12, Inputs!$D$5, Inputs!$B$5) -> 229.21395 | E197: =C197 * (Inputs!$C$5/12) -> 45.172964 | F197: =D197 - E197 -> 184.04098 | G197: =C197 - F197 -> 9671.8784 | H197: =D197 -> 229.21395
... A244: =Inputs!$A$5 -> L4 | B244: 60 | C244: =G243 -> 228.16818 | D244: =-PMT(Inputs!$C$5/12, Inputs!$D$5, Inputs!$B$5) -> 229.21395 | E244: =C244 * (Inputs!$C$5/12) -> 1.0457708 | F244: =D244 - E244 -> 228.16818 | G244: =C244 - F244 -> 2.3305802e-12 | H244: =D244 -> 229.21395
A246: =Inputs!$A$6 -> L5 | B246: 1 | C246: =Inputs!$B$6 -> 40000 | D246: =-PMT(Inputs!$C$6/12, Inputs!$D$6, Inputs!$B$6) -> 830.33421 | E246: =C246 * (Inputs!$C$6/12) -> 300 | F246: =D246 - E246 -> 530.33421 | G246: =C246 - F246 -> 39469.666 | H246: =D246 -> 830.33421
A247: =Inputs!$A$6 -> L5 | B247: 2 | C247: =G246 -> 39469.666 | D247: =-PMT(Inputs!$C$6/12, Inputs!$D$6, Inputs!$B$6) -> 830.33421 | E247: =C247 * (Inputs!$C$6/12) -> 296.02249 | F247: =D247 - E247 -> 534.31172 | G247: =C247 - F247 -> 38935.354 | H247: =D247 -> 830.33421
A248: =Inputs!$A$6 -> L5 | B248: 3 | C248: =G247 -> 38935.354 | D248: =-PMT(Inputs!$C$6/12, Inputs!$D$6, Inputs!$B$6) -> 830.33421 | E248: =C248 * (Inputs!$C$6/12) -> 292.01516 | F248: =D248 - E248 -> 538.31905 | G248: =C248 - F248 -> 38397.035 | H248: =D246 -> 830.33421
A249: =Inputs!$A$6 -> L5 | B249: 4 | C249: =G248 -> 38397.035 | D249: =-PMT(Inputs!$C$6/12, Inputs!$D$6, Inputs!$B$6) -> 830.33421 | E249: =C249 * (Inputs!$C$6/12) -> 287.97776 | F249: =D249 - E249 -> 542.35645 | G249: =C249 - F249 -> 37854.679 | H249: =D247 -> 830.33421
A250: =Inputs!$A$6 -> L5 | B250: 5 | C250: =G249 -> 37854.679 | D250: =-PMT(Inputs!$C$6/12, Inputs!$D$6, Inputs!$B$6) -> 830.33421 | E250: =C250 * (Inputs!$C$6/12) -> 283.91009 | F250: =D250 - E250 -> 546.42412 | G250: =C250 - F250 -> 37308.254 | H250: =D248 -> 830.33421
A251: =Inputs!$A$6 -> L5 | B251: 6 | C251: =G250 -> 37308.254 | D251: =-PMT(Inputs!$C$6/12, Inputs!$D$6, Inputs!$B$6) -> 830.33421 | E251: =C251 * (Inputs!$C$6/12) -> 279.81191 | F251: =D251 - E251 -> 550.5223 | G251: =C251 - F251 -> 36757.732 | H251: =D249 -> 830.33421
A252: =Inputs!$A$6 -> L5 | B252: 7 | C252: =G251 -> 36757.732 | D252: =-PMT(Inputs!$C$6/12, Inputs!$D$6, Inputs!$B$6) -> 830.33421 | E252: =C252 * (Inputs!$C$6/12) -> 275.68299 | F252: =D252 - E252 -> 554.65122 | G252: =C252 - F252 -> 36203.081 | H252: =D250 -> 830.33421
A253: =Inputs!$A$6 -> L5 | B253: 8 | C253: =G252 -> 36203.081 | D253: =-PMT(Inputs!$C$6/12, Inputs!$D$6, Inputs!$B$6) -> 830.33421 | E253: =C253 * (Inputs!$C$6/12) -> 271.52311 | F253: =D253 - E253 -> 558.8111 | G253: =C253 - F253 -> 35644.27 | H253: =D251 -> 830.33421
A254: =Inputs!$A$6 -> L5 | B254: 9 | C254: =G253 -> 35644.27 | D254: =-PMT(Inputs!$C$6/12, Inputs!$D$6, Inputs!$B$6) -> 830.33421 | E254: =C254 * (Inputs!$C$6/12) -> 267.33202 | F254: =D254 - E254 -> 563.00219 | G254: =C254 - F254 -> 35081.268 | H254: =D252 -> 830.33421
A255: =Inputs!$A$6 -> L5 | B255: 10 | C255: =G254 -> 35081.268 | D255: =-PMT(Inputs!$C$6/12, Inputs!$D$6, Inputs!$B$6) -> 830.33421 | E255: =C255 * (Inputs!$C$6/12) -> 263.10951 | F255: =D255 - E255 -> 567.2247 | G255: =C255 - F255 -> 34514.043 | H255: =D253 -> 830.33421
A256: =Inputs!$A$6 -> L5 | B256: 11 | C256: =G255 -> 34514.043 | D256: =-PMT(Inputs!$C$6/12, Inputs!$D$6, Inputs!$B$6) -> 830.33421 | E256: =C256 * (Inputs!$C$6/12) -> 258.85532 | F256: =D256 - E256 -> 571.47889 | G256: =C256 - F256 -> 33942.564 | H256: =D254 -> 830.33421
A257: =Inputs!$A$6 -> L5 | B257: 12 | C257: =G256 -> 33942.564 | D257: =-PMT(Inputs!$C$6/12, Inputs!$D$6, Inputs!$B$6) -> 830.33421 | E257: =C257 * (Inputs!$C$6/12) -> 254.56923 | F257: =D257 - E257 -> 575.76498 | G257: =C257 - F257 -> 33366.799 | H257: =D255 -> 830.33421
A258: =Inputs!$A$6 -> L5 | B258: 13 | C258: =G257 -> 33366.799 | D258: =-PMT(Inputs!$C$6/12, Inputs!$D$6, Inputs!$B$6) -> 830.33421 | E258: =C258 * (Inputs!$C$6/12) -> 250.25099 | F258: =D258 - E258 -> 580.08322 | G258: =C258 - F258 -> 32786.716 | H258: =D256 -> 830.33421
A259: =Inputs!$A$6 -> L5 | B259: 14 | C259: =G258 -> 32786.716 | D259: =-PMT(Inputs!$C$6/12, Inputs!$D$6, Inputs!$B$6) -> 830.33421 | E259: =C259 * (Inputs!$C$6/12) -> 245.90037 | F259: =D259 - E259 -> 584.43384 | G259: =C259 - F259 -> 32202.282 | H259: =D257 -> 830.33421
... A304: =Inputs!$A$6 -> L5 | B304: 59 | C304: =G303 -> 1642.171 | D304: =-PMT(Inputs!$C$6/12, Inputs!$D$6, Inputs!$B$6) -> 830.33421 | E304: =C304 * (Inputs!$C$6/12) -> 12.316282 | F304: =D304 - E304 -> 818.01793 | G304: =C304 - F304 -> 824.15306 | H304: =D302 -> 830.33421
A305: =Inputs!$A$6 -> L5 | B305: 60 | C305: =G304 -> 824.15306 | D305: =-PMT(Inputs!$C$6/12, Inputs!$D$6, Inputs!$B$6) -> 830.33421 | E305: =C305 * (Inputs!$C$6/12) -> 6.181148 | F305: =D305 - E305 -> 824.15306 | G305: =C305 - F305 -> -1.2732926e-11 | H305: =D305 -> 830.33421
A307: =Inputs!$A$7 -> L6 | B307: 1 | C307: =Inputs!$B$7 -> 18000 | D307: =-PMT(Inputs!$C$7/12, Inputs!$D$7, Inputs!$B$7) -> 354.72554 | E307: =C307 * (Inputs!$C$7/12) -> 102 | F307: =D307 - E307 -> 252.72554 | G307: =C307 - F307 -> 17747.274 | H307: =D307 -> 354.72554
A308: =Inputs!$A$7 -> L6 | B308: 2 | C308: =G307 -> 17747.274 | D308: =-PMT(Inputs!$C$7/12, Inputs!$D$7, Inputs!$B$7) -> 354.72554 | E308: =C308 * (Inputs!$C$7/12) -> 100.56789 | F308: =D308 - E308 -> 254.15765 | G308: =C308 - F308 -> 17493.117 | H308: =D308 -> 354.72554
A309: =Inputs!$A$7 -> L6 | B309: 3 | C309: =G308 -> 17493.117 | D309: =-PMT(Inputs!$C$7/12, Inputs!$D$7, Inputs!$B$7) -> 354.72554 | E309: =C309 * (Inputs!$C$7/12) -> 99.127662 | F309: =D309 - E309 -> 255.59787 | G309: =C309 - F309 -> 17237.519 | H309: =D307 -> 354.72554
A310: =Inputs!$A$7 -> L6 | B310: 4 | C310: =G309 -> 17237.519 | D310: =-PMT(Inputs!$C$7/12, Inputs!$D$7, Inputs!$B$7) -> 354.72554 | E310: =C310 * (Inputs!$C$7/12) -> 97.679274 | F310: =D310 - E310 -> 257.04626 | G310: =C310 - F310 -> 16980.473 | H310: =D308 -> 354.72554
A311: =Inputs!$A$7 -> L6 | B311: 5 | C311: =G310 -> 16980.473 | D311: =-PMT(Inputs!$C$7/12, Inputs!$D$7, Inputs!$B$7) -> 354.72554 | E311: =C311 * (Inputs!$C$7/12) -> 96.222679 | F311: =D311 - E311 -> 258.50286 | G311: =C311 - F311 -> 16721.97 | H311: =D309 -> 354.72554
A312: =Inputs!$A$7 -> L6 | B312: 6 | C312: =G311 -> 16721.97 | D312: =-PMT(Inputs!$C$7/12, Inputs!$D$7, Inputs!$B$7) -> 354.72554 | E312: =C312 * (Inputs!$C$7/12) -> 94.757829 | F312: =D312 - E312 -> 259.96771 | G312: =C312 - F312 -> 16462.002 | H312: =D310 -> 354.72554
A313: =Inputs!$A$7 -> L6 | B313: 7 | C313: =G312 -> 16462.002 | D313: =-PMT(Inputs!$C$7/12, Inputs!$D$7, Inputs!$B$7) -> 354.72554 | E313: =C313 * (Inputs!$C$7/12) -> 93.284679 | F313: =D313 - E313 -> 261.44086 | G313: =C313 - F313 -> 16200.561 | H313: =D311 -> 354.72554
A314: =Inputs!$A$7 -> L6 | B314: 8 | C314: =G313 -> 16200.561 | D314: =-PMT(Inputs!$C$7/12, Inputs!$D$7, Inputs!$B$7) -> 354.72554 | E314: =C314 * (Inputs!$C$7/12) -> 91.80318 | F314: =D314 - E314 -> 262.92236 | G314: =C314 - F314 -> 15937.639 | H314: =D312 -> 354.72554
A315: =Inputs!$A$7 -> L6 | B315: 9 | C315: =G314 -> 15937.639 | D315: =-PMT(Inputs!$C$7/12, Inputs!$D$7, Inputs!$B$7) -> 354.72554 | E315: =C315 * (Inputs!$C$7/12) -> 90.313287 | F315: =D315 - E315 -> 264.41225 | G315: =C315 - F315 -> 15673.227 | H315: =D313 -> 354.72554
A316: =Inputs!$A$7 -> L6 | B316: 10 | C316: =G315 -> 15673.227 | D316: =-PMT(Inputs!$C$7/12, Inputs!$D$7, Inputs!$B$7) -> 354.72554 | E316: =C316 * (Inputs!$C$7/12) -> 88.814951 | F316: =D316 - E316 -> 265.91058 | G316: =C316 - F316 -> 15407.316 | H316: =D314 -> 354.72554
A317: =Inputs!$A$7 -> L6 | B317: 11 | C317: =G316 -> 15407.316 | D317: =-PMT(Inputs!$C$7/12, Inputs!$D$7, Inputs!$B$7) -> 354.72554 | E317: =C317 * (Inputs!$C$7/12) -> 87.308124 | F317: =D317 - E317 -> 267.41741 | G317: =C317 - F317 -> 15139.899 | H317: =D315 -> 354.72554
A318: =Inputs!$A$7 -> L6 | B318: 12 | C318: =G317 -> 15139.899 | D318: =-PMT(Inputs!$C$7/12, Inputs!$D$7, Inputs!$B$7) -> 354.72554 | E318: =C318 * (Inputs!$C$7/12) -> 85.792759 | F318: =D318 - E318 -> 268.93278 | G318: =C318 - F318 -> 14870.966 | H318: =D316 -> 354.72554
A319: =Inputs!$A$7 -> L6 | B319: 13 | C319: =G318 -> 14870.966 | D319: =-PMT(Inputs!$C$7/12, Inputs!$D$7, Inputs!$B$7) -> 354.72554 | E319: =C319 * (Inputs!$C$7/12) -> 84.268807 | F319: =D319 - E319 -> 270.45673 | G319: =C319 - F319 -> 14600.509 | H319: =D317 -> 354.72554
A320: =Inputs!$A$7 -> L6 | B320: 14 | C320: =G319 -> 14600.509 | D320: =-PMT(Inputs!$C$7/12, Inputs!$D$7, Inputs!$B$7) -> 354.72554 | E320: =C320 * (Inputs!$C$7/12) -> 82.736219 | F320: =D320 - E320 -> 271.98932 | G320: =C320 - F320 -> 14328.52 | H320: =D318 -> 354.72554
... A365: =Inputs!$A$7 -> L6 | B365: 59 | C365: =G364 -> 703.46598 | D365: =-PMT(Inputs!$C$7/12, Inputs!$D$7, Inputs!$B$7) -> 354.72554 | E365: =C365 * (Inputs!$C$7/12) -> 3.9863072 | F365: =D365 - E365 -> 350.73923 | G365: =C365 - F365 -> 352.72675 | H365: =D363 -> 354.72554
A366: =Inputs!$A$7 -> L6 | B366: 60 | C366: =G365 -> 352.72675 | D366: =-PMT(Inputs!$C$7/12, Inputs!$D$7, Inputs!$B$7) -> 354.72554 | E366: =C366 * (Inputs!$C$7/12) -> 1.9987849 | F366: =D366 - E366 -> 352.72675 | G366: =C366 - F366 -> 5.286438e-12 | H366: =D366 -> 354.72554
A368: =Inputs!$A$8 -> L7 | B368: 1 | C368: =Inputs!$B$8 -> 22000 | D368: =-PMT(Inputs!$C$8/12, Inputs!$D$8, Inputs!$B$8) -> 440.83487 | E368: =C368 * (Inputs!$C$8/12) -> 137.5 | F368: =D368 - E368 -> 303.33487 | G368: =C368 - F368 -> 21696.665 | H368: =D368 -> 440.83487
A369: =Inputs!$A$8 -> L7 | B369: 2 | C369: =G368 -> 21696.665 | D369: =-PMT(Inputs!$C$8/12, Inputs!$D$8, Inputs!$B$8) -> 440.83487 | E369: =C369 * (Inputs!$C$8/12) -> 135.60416 | F369: =D369 - E369 -> 305.23071 | G369: =C369 - F369 -> 21391.434 | H369: =D369 -> 440.83487
A370: =Inputs!$A$8 -> L7 | B370: 3 | C370: =G369 -> 21391.434 | D370: =-PMT(Inputs!$C$8/12, Inputs!$D$8, Inputs!$B$8) -> 440.83487 | E370: =C370 * (Inputs!$C$8/12) -> 133.69647 | F370: =D370 - E370 -> 307.1384 | G370: =C370 - F370 -> 21084.296 | H370: =D368 -> 440.83487
A371: =Inputs!$A$8 -> L7 | B371: 4 | C371: =G370 -> 21084.296 | D371: =-PMT(Inputs!$C$8/12, Inputs!$D$8, Inputs!$B$8) -> 440.83487 | E371: =C371 * (Inputs!$C$8/12) -> 131.77685 | F371: =D371 - E371 -> 309.05802 | G371: =C371 - F371 -> 20775.238 | H371: =D369 -> 440.83487
A372: =Inputs!$A$8 -> L7 | B372: 5 | C372: =G371 -> 20775.238 | D372: =-PMT(Inputs!$C$8/12, Inputs!$D$8, Inputs!$B$8) -> 440.83487 | E372: =C372 * (Inputs!$C$8/12) -> 129.84524 | F372: =D372 - E372 -> 310.98963 | G372: =C372 - F372 -> 20464.248 | H372: =D370 -> 440.83487
A373: =Inputs!$A$8 -> L7 | B373: 6 | C373: =G372 -> 20464.248 | D373: =-PMT(Inputs!$C$8/12, Inputs!$D$8, Inputs!$B$8) -> 440.83487 | E373: =C373 * (Inputs!$C$8/12) -> 127.90155 | F373: =D373 - E373 -> 312.93332 | G373: =C373 - F373 -> 20151.315 | H373: =D371 -> 440.83487
A374: =Inputs!$A$8 -> L7 | B374: 7 | C374: =G373 -> 20151.315 | D374: =-PMT(Inputs!$C$8/12, Inputs!$D$8, Inputs!$B$8) -> 440.83487 | E374: =C374 * (Inputs!$C$8/12) -> 125.94572 | F374: =D374 - E374 -> 314.88915 | G374: =C374 - F374 -> 19836.426 | H374: =D372 -> 440.83487
A375: =Inputs!$A$8 -> L7 | B375: 8 | C375: =G374 -> 19836.426 | D375: =-PMT(Inputs!$C$8/12, Inputs!$D$8, Inputs!$B$8) -> 440.83487 | E375: =C375 * (Inputs!$C$8/12) -> 123.97766 | F375: =D375 - E375 -> 316.85721 | G375: =C375 - F375 -> 19519.569 | H375: =D373 -> 440.83487
A376: =Inputs!$A$8 -> L7 | B376: 9 | C376: =G375 -> 19519.569 | D376: =-PMT(Inputs!$C$8/12, Inputs!$D$8, Inputs!$B$8) -> 440.83487 | E376: =C376 * (Inputs!$C$8/12) -> 121.9973 | F376: =D376 - E376 -> 318.83756 | G376: =C376 - F376 -> 19200.731 | H376: =D374 -> 440.83487
A377: =Inputs!$A$8 -> L7 | B377: 10 | C377: =G376 -> 19200.731 | D377: =-PMT(Inputs!$C$8/12, Inputs!$D$8, Inputs!$B$8) -> 440.83487 | E377: =C377 * (Inputs!$C$8/12) -> 120.00457 | F377: =D377 - E377 -> 320.8303 | G377: =C377 - F377 -> 18879.901 | H377: =D375 -> 440.83487
A378: =Inputs!$A$8 -> L7 | B378: 11 | C378: =G377 -> 18879.901 | D378: =-PMT(Inputs!$C$8/12, Inputs!$D$8, Inputs!$B$8) -> 440.83487 | E378: =C378 * (Inputs!$C$8/12) -> 117.99938 | F378: =D378 - E378 -> 322.83549 | G378: =C378 - F378 -> 18557.065 | H378: =D376 -> 440.83487
...

Sheet Portfolio
A1: Month | B1: Total_CF
A2: 1 | B2: =SUMIF(Schedule!$B$2:$B$610, A2, Schedule!$H$2:$H$610) -> 5006.1684
A3: 2 | B3: =SUMIF(Schedule!$B$2:$B$610, A3, Schedule!$H$2:$H$610) -> 5006.1684
A4: 3 | B4: =SUMIF(Schedule!$B$2:$B$610, A4, Schedule!$H$2:$H$610) -> 5006.1684
A5: 4 | B5: =SUMIF(Schedule!$B$2:$B$610, A5, Schedule!$H$2:$H$610) -> 5006.1684
A6: 5 | B6: =SUMIF(Schedule!$B$2:$B$610, A6, Schedule!$H$2:$H$610) -> 5006.1684
A7: 6 | B7: =SUMIF(Schedule!$B$2:$B$610, A7, Schedule!$H$2:$H$610) -> 5006.1684
A8: 7 | B8: =SUMIF(Schedule!$B$2:$B$610, A8, Schedule!$H$2:$H$610) -> 5006.1684
A9: 8 | B9: =SUMIF(Schedule!$B$2:$B$610, A9, Schedule!$H$2:$H$610) -> 5006.1684
A10: 9 | B10: =SUMIF(Schedule!$B$2:$B$610, A10, Schedule!$H$2:$H$610) -> 5006.1684
A11: 10 | B11: =SUMIF(Schedule!$B$2:$B$610, A11, Schedule!$H$2:$H$610) -> 5006.1684
A12: 11 | B12: =SUMIF(Schedule!$B$2:$B$610, A12, Schedule!$H$2:$H$610) -> 5006.1684
A13: 12 | B13: =SUMIF(Schedule!$B$2:$B$610, A13, Schedule!$H$2:$H$610) -> 5006.1684
... A61: 60 | B61: =SUMIF(Schedule!$B$2:$B$610, A61, Schedule!$H$2:$H$610) -> 5006.1684

Sheet Valuation
A1: Month | B1: Portfolio_CF | C1: DF_low | D1: DF_base | E1: DF_high | F1: PV_low | G1: PV_base | H1: PV_high
A2: 1 | B2: =Portfolio!B2 -> 5006.1684 | C2: =1/(1+r_low_m)^A2 -> 0.9975398 | D2: =1/(1+r_base_m)^A2 -> 0.99594241 | E2: =1/(1+r_high_m)^A2 -> 0.9936071 | F2: =B2*C2 -> 4993.8522 | G2: =B2*D2 -> 4985.8554 | H2: =B2*E2 -> 4974.1645
A3: 2 | B3: =Portfolio!B3 -> 5006.1684 | C3: =1/(1+r_low_m)^A3 -> 0.99508565 | D3: =1/(1+r_base_m)^A3 -> 0.99190128 | E3: =1/(1+r_high_m)^A3 -> 0.98725507 | F3: =B3*C3 -> 4981.5664 | G3: =B3*D3 -> 4965.6249 | H3: =B3*E3 -> 4942.3652
A4: 3 | B4: =Portfolio!B4 -> 5006.1684 | C4: =1/(1+r_low_m)^A4 -> 0.99263754 | D4: =1/(1+r_base_m)^A4 -> 0.98787655 | E4: =1/(1+r_high_m)^A4 -> 0.98094365 | F4: =B4*C4 -> 4969.3107 | G4: =B4*D4 -> 4945.4764 | H4: =B4*E4 -> 4910.7691
A5: 4 | B5: =Portfolio!B5 -> 5006.1684 | C5: =1/(1+r_low_m)^A5 -> 0.99019545 | D5: =1/(1+r_base_m)^A5 -> 0.98386815 | E5: =1/(1+r_high_m)^A5 -> 0.97467258 | F5: =B5*C5 -> 4957.0852 | G5: =B5*D5 -> 4925.4097 | H5: =B5*E5 -> 4879.3751
A6: 5 | B6: =Portfolio!B6 -> 5006.1684 | C6: =1/(1+r_low_m)^A6 -> 0.98775937 | D6: =1/(1+r_base_m)^A6 -> 0.97987601 | E6: =1/(1+r_high_m)^A6 -> 0.9684416 | F6: =B6*C6 -> 4944.8898 | G6: =B6*D6 -> 4905.4243 | H6: =B6*E6 -> 4848.1817
A7: 6 | B7: =Portfolio!B7 -> 5006.1684 | C7: =1/(1+r_low_m)^A7 -> 0.98532928 | D7: =1/(1+r_base_m)^A7 -> 0.97590007 | E7: =1/(1+r_high_m)^A7 -> 0.96225045 | F7: =B7*C7 -> 4932.7243 | G7: =B7*D7 -> 4885.5201 | H7: =B7*E7 -> 4817.1878
A8: 7 | B8: =Portfolio!B8 -> 5006.1684 | C8: =1/(1+r_low_m)^A8 -> 0.98290517 | D8: =1/(1+r_base_m)^A8 -> 0.97194027 | E8: =1/(1+r_high_m)^A8 -> 0.95609888 | F8: =B8*C8 -> 4920.5888 | G8: =B8*D8 -> 4865.6967 | H8: =B8*E8 -> 4786.392
A9: 8 | B9: =Portfolio!B9 -> 5006.1684 | C9: =1/(1+r_low_m)^A9 -> 0.98048702 | D9: =1/(1+r_base_m)^A9 -> 0.96799653 | E9: =1/(1+r_high_m)^A9 -> 0.94998664 | F9: =B9*C9 -> 4908.4832 | G9: =B9*D9 -> 4845.9537 | H9: =B9*E9 -> 4755.7931
A10: 9 | B10: =Portfolio!B10 -> 5006.1684 | C10: =1/(1+r_low_m)^A10 -> 0.97807483 | D10: =1/(1+r_base_m)^A10 -> 0.96406879 | E10: =1/(1+r_high_m)^A10 -> 0.94391347 | F10: =B10*C10 -> 4896.4073 | G10: =B10*D10 -> 4826.2908 | H10: =B10*E10 -> 4725.3898
A11: 10 | B11: =Portfolio!B11 -> 5006.1684 | C11: =1/(1+r_low_m)^A11 -> 0.97566857 | D11: =1/(1+r_base_m)^A11 -> 0.960157 | E11: =1/(1+r_high_m)^A11 -> 0.93787913 | F11: =B11*C11 -> 4884.3612 | G11: =B11*D11 -> 4806.7076 | H11: =B11*E11 -> 4695.1809
A12: 11 | B12: =Portfolio!B12 -> 5006.1684 | C12: =1/(1+r_low_m)^A12 -> 0.97326822 | D12: =1/(1+r_base_m)^A12 -> 0.95626107 | E12: =1/(1+r_high_m)^A12 -> 0.93188336 | F12: =B12*C12 -> 4872.3446 | G12: =B12*D12 -> 4787.204 | H12: =B12*E12 -> 4665.1651
A13: 12 | B13: =Portfolio!B13 -> 5006.1684 | C13: =1/(1+r_low_m)^A13 -> 0.97087379 | D13: =1/(1+r_base_m)^A13 -> 0.95238095 | E13: =1/(1+r_high_m)^A13 -> 0.92592593 | F13: =B13*C13 -> 4860.3577 | G13: =B13*D13 -> 4767.7795 | H13: =B13*E13 -> 4635.3411
... A61: 60 | B61: =Portfolio!B61 -> 5006.1684 | C61: =1/(1+r_low_m)^A61 -> 0.86260878 | D61: =1/(1+r_base_m)^A61 -> 0.78352617 | E61: =1/(1+r_high_m)^A61 -> 0.6805832 | F61: =B61*C61 -> 4318.3649 | G61: =B61*D61 -> 3922.464 | H61: =B61*E61 -> 3407.1141
F62: PV_low | G62: PV_base | H62: PV_high
A63: Total PV | F63: =SUM(F2:F61) -> 278884.16 | G63: =SUM(G2:G61) -> 265996.94 | H63: =SUM(H2:H61) -> 248530.75

Sheet Summary
A1: LoanID | B1: Principal | C1: AnnualRate | D1: TermMonths | E1: PD_Annual | F1: LGD
A2: L1 | B2: 25000 | C2: 0.08 | D2: 60 | E2: 0.04 | F2: =Inputs!$G2 -> 0.4
A3: L2 | B3: 15000 | C3: 0.065 | D3: 60 | E3: 0.03 | F3: =Inputs!$G3 -> 0.5
A4: L3 | B4: 30000 | C4: 0.072 | D4: 60 | E4: 0.05 | F4: =Inputs!$G4 -> 0.25
A5: L4 | B5: 12000 | C5: 0.055 | D5: 60 | E5: 0.02 | F5: =Inputs!$G5 -> 0.6
A6: L5 | B6: 40000 | C6: 0.09 | D6: 60 | E6: 0.06 | F6: =Inputs!$G6 -> 0.5
A7: L6 | B7: 18000 | C7: 0.068 | D7: 60 | E7: 0.03 | F7: =Inputs!$G7 -> 0.45
A8: L7 | B8: 22000 | C8: 0.075 | D8: 60 | E8: 0.04 | F8: =Inputs!$G8 -> 0.3
A9: L8 | B9: 50000 | C9: 0.085 | D9: 60 | E9: 0.07 | F9: =Inputs!$G9 -> 0.2
A10: L9 | B10: 27000 | C10: 0.07 | D10: 60 | E10: 0.04 | F10: =Inputs!$G10 -> 0.35
A11: L10 | B11: 10000 | C11: 0.06 | D11: 60 | E11: 0.02 | F11: =Inputs!$G11 -> 0.4
